pynamicgain/__init__.py
pynamicgain/__main__.py
pynamicgain/analysis.py
pynamicgain/new_setup.py
pynamicgain/stimulus_generation.py
pynamicgain/default_configs/default_configs.toml
pynamicgain/default_configs/matploltlib.mplstyle
PynamicGain-0.0.9.dist-info/LICENSE
PynamicGain-0.0.9.dist-info/METADATA
PynamicGain-0.0.9.dist-info/WHEEL
PynamicGain-0.0.9.dist-info/entry_points.txt
PynamicGain-0.0.9.dist-info/top_level.txt
PynamicGain-0.0.9.dist-info/RECORD
